modules/module_3_8_bit_SAR_ADC/part_3_algorithm/sar_algo.v
//Verilog HDL for "8_bit_SAR_ADC", "sar_algorithm" "functional"

module sar_algorithm (
    input wire Op,
    input wire En,
    input wire Om,
    input wire clk,
    input wire rst,
    output reg [7:0] B,   // 8-bit
    output reg [7:0] BN,  // 8-bit
    output reg [7:0] D    // 8-bit
);

reg [2:0] counter = 3'b000; // 3-bit counter

always @(posedge clk) begin
    if (En && !rst && (Op ^ Om)) begin
        if (counter != 3'b111) begin  // Limit to 8
            D[counter] <= Op;

            if (Op) begin
                B[counter] <= 1'b1;
                BN[counter] <= 1'b0;
            end else if (Om) begin
                B[counter] <= 1'b0;
                BN[counter] <= 1'b1;
            end

            counter <= counter + 1'b1;
        end
    end else if (rst) begin
        B <= 8'b00000000;
        BN <= 8'b00000000;
        D <= 8'b00000000;
        counter <= 3'b000;
    end
end

endmodule

modules/module_3_8_bit_SAR_ADC/part_2_algorithm/verilog/sar_algo_tb.v
`timescale 1ns / 1ps

module sar_algorithm_tb();

    reg Op, En, Om, clk, rst;
    wire [7:0] B, BN, D;
    
    // Instantiate the SAR algorithm module
    sar_algorithm uut (
        .Op(Op),
        .En(En),
        .Om(Om),
        .clk(clk),
        .rst(rst),
        .B(B),
        .BN(BN),
        .D(D)
    );
    
    // Clock generation
    always #5 clk = ~clk; // 10ns period (100 MHz)
    
    initial begin
    	$dumpfile("sar_algo_tb.vcd");
    	$dumpvars(0, sar_algorithm_tb);
        // Initialize signals
        clk = 0;
        rst = 1;
        En = 0;
        Op = 0;
        Om = 0;
        
        // Apply reset
        #10 rst = 0;
        
        // Enable SAR ADC and provide inputs
        #10 En = 1;
        
        // Provide input pattern
        #10 Op = 1; Om = 0;
        #10 Op = 0; Om = 1;
        #10 Op = 1; Om = 0;
        #10 Op = 0; Om = 1;
        #10 Op = 1; Om = 0;
        #10 Op = 0; Om = 1;
        #10 Op = 1; Om = 0;
        #10 Op = 0; Om = 1;
        
        // Disable SAR ADC
        #10 En = 0;
        
        // Apply reset again
        #20 rst = 1;
        #10 rst = 0;
        
        // End simulation
        #50 $finish;
    end
    
endmodule

modules/module_3_8_bit_SAR_ADC/part_2_algorithm/verilog/sar_algo_tb.vcd
$date
	Mon Mar 10 09:58:33 2025
$end
$version
	Icarus Verilog
$end
$timescale
	1ps
$end
$scope module sar_algorithm_tb $end
$var wire 8 ! D [7:0] $end
$var wire 8 " BN [7:0] $end
$var wire 8 # B [7:0] $end
$var reg 1 $ En $end
$var reg 1 % Om $end
$var reg 1 & Op $end
$var reg 1 ' clk $end
$var reg 1 ( rst $end
$scope module uut $end
$var wire 1 $ En $end
$var wire 1 % Om $end
$var wire 1 & Op $end
$var wire 1 ' clk $end
$var wire 1 ( rst $end
$var reg 8 ) B [7:0] $end
$var reg 8 * BN [7:0] $end
$var reg 8 + D [7:0] $end
$var reg 3 , counter [2:0] $end
$upscope $end
$upscope $end
$enddefinitions $end
#0
$dumpvars
b0 ,
bx +
bx *
bx )
1(
0'
0&
0%
0$
bx #
bx "
bx !
$end
#5000
b0 !
b0 +
b0 "
b0 *
b0 #
b0 )
1'
#10000
0'
0(
#15000
1'
#20000
0'
1$
#25000
1'
#30000
0'
1&
#35000
b1 ,
b1 #
b1 )
b1 !
b1 +
1'
#40000
0'
1%
0&
#45000
b10 ,
b10 "
b10 *
1'
#50000
0'
0%
1&
#55000
b11 ,
b101 #
b101 )
b101 !
b101 +
1'
#60000
0'
1%
0&
#65000
b100 ,
b1010 "
b1010 *
1'
#70000
0'
0%
1&
#75000
b101 ,
b10101 #
b10101 )
b10101 !
b10101 +
1'
#80000
0'
1%
0&
#85000
b110 ,
b101010 "
b101010 *
1'
#90000
0'
0%
1&
#95000
b111 ,
b1010101 #
b1010101 )
b1010101 !
b1010101 +
1'
#100000
0'
1%
0&
#105000
1'
#110000
0'
0$
#115000
1'
#120000
0'
#125000
1'
#130000
0'
1(
#135000
b0 ,
b0 !
b0 +
b0 "
b0 *
b0 #
b0 )
1'
#140000
0'
0(
